CHANGES.txt
CONTRIBUTORS.txt
README.txt
bootstrap.py
buildout.cfg
setup.cfg
setup.py
topp/__init__.py
topp.recipes.cfgtemplate.egg-info/PKG-INFO
topp.recipes.cfgtemplate.egg-info/SOURCES.txt
topp.recipes.cfgtemplate.egg-info/dependency_links.txt
topp.recipes.cfgtemplate.egg-info/entry_points.txt
topp.recipes.cfgtemplate.egg-info/namespace_packages.txt
topp.recipes.cfgtemplate.egg-info/not-zip-safe
topp.recipes.cfgtemplate.egg-info/requires.txt
topp.recipes.cfgtemplate.egg-info/top_level.txt
topp/recipes/__init__.py
topp/recipes/cfgtemplate/README.txt
topp/recipes/cfgtemplate/__init__.py
topp/recipes/cfgtemplate/template.py
topp/recipes/cfgtemplate/tests/__init__.py
topp/recipes/cfgtemplate/tests/test_docs.py