Metadata-Version: 1.0
Name: topp.recipes.cfgtemplate
Version: 0.1.0dev-r19469
Summary: Provides template substitution for other recipe configurations in the same buildout.cfg file.
Home-page: http://topp.openplans.org/
Author: Rob Miller
Author-email: robm@openplans.org
License: GPLv3
Keywords: buildout
Platform: UNKNOWN
Classifier: Framework :: Buildout
Classifier: Intended Audience :: Developers
Classifier: Topic :: Software Development :: Build Tools
Classifier: Topic :: Software Development :: Libraries :: Python Modules
